Metadata-Version: 2.1
Name: spackl
Version: 0.1.0
Summary: Utility for unified querying across data sources
Home-page: https://github.com/aaronbiller/spackl
Author: Aaron Biller
Author-email: aaronbiller@gmail.com
License: MIT
Keywords: utility query database csv file
Platform: UNKNOWN
Classifier: Development Status :: 3 - Alpha
Classifier: Intended Audience :: Developers
Classifier: License :: OSI Approved :: MIT License
Classifier: Programming Language :: Python :: 2
Classifier: Programming Language :: Python :: 2.7
Classifier: Programming Language :: Python :: 3
Classifier: Programming Language :: Python :: 3.6
Classifier: Programming Language :: Python :: 3.7
Classifier: Topic :: Database
Classifier: Topic :: Utilities
